setup.py
flask_datatables/__init__.py
flask_datatables.egg-info/PKG-INFO
flask_datatables.egg-info/SOURCES.txt
flask_datatables.egg-info/dependency_links.txt
flask_datatables.egg-info/not-zip-safe
flask_datatables.egg-info/requires.txt
flask_datatables.egg-info/top_level.txt
flask_datatables/views/__init__.py
flask_datatables/views/apihelpers.py
flask_datatables/views/search.py