Metadata-Version: 1.1
Name: flask-datatables
Version: 0.6.10
Summary: Integrates SQLAlchemy with DataTables (framework Flask)
Home-page: https://github.com/tahoe/flask_datatables/
Author: Dennis Durling
Author-email: djdtahoe@gmail.com
License: MIT
Download-URL: https://github.com/tahoe/flask_datatables/tarball/0.6.10
Keywords: datatables sqlalchemy flask
Platform: UNKNOWN
Classifier: Environment :: Web Environment
Classifier: Framework :: Flask
Classifier: Intended Audience :: Developers
Classifier: License :: OSI Approved :: MIT License
Classifier: Programming Language :: Python
Classifier: Programming Language :: Python :: 2.7
Classifier: Programming Language :: Python :: 3.3
Classifier: Programming Language :: Python :: 3.4
Classifier: Programming Language :: Python :: 3.5
Classifier: Topic :: Internet :: WWW/HTTP
Classifier: Topic :: Software Development :: Libraries
Classifier: Topic :: Software Development :: Libraries :: Python Modules
